pythagoras/__init__.py
pythagoras/_version_info.py
pythagoras/py.typed
pythagoras/_110_supporting_utilities/__init__.py
pythagoras/_110_supporting_utilities/base_16_32_converters.py
pythagoras/_110_supporting_utilities/constants_for_signatures_and_converters.py
pythagoras/_110_supporting_utilities/current_date_gmt_str.py
pythagoras/_110_supporting_utilities/hash_signature.py
pythagoras/_110_supporting_utilities/long_infoname.py
pythagoras/_110_supporting_utilities/node_signature.py
pythagoras/_110_supporting_utilities/random_signature.py
pythagoras/_210_basic_portals/__init__.py
pythagoras/_210_basic_portals/basic_portal_accessors.py
pythagoras/_210_basic_portals/basic_portal_core_classes.py
pythagoras/_210_basic_portals/default_portal_base_dir.py
pythagoras/_210_basic_portals/portal_description_helpers.py
pythagoras/_210_basic_portals/portal_tester.py
pythagoras/_220_data_portals/__init__.py
pythagoras/_220_data_portals/data_portal_core_classes.py
pythagoras/_220_data_portals/kw_args.py
pythagoras/_220_data_portals/ready_and_get.py
pythagoras/_230_tunable_portals/__init__.py
pythagoras/_230_tunable_portals/tunable_portal_core_classes.py
pythagoras/_310_ordinary_code_portals/__init__.py
pythagoras/_310_ordinary_code_portals/code_normalizer.py
pythagoras/_310_ordinary_code_portals/function_error_exception.py
pythagoras/_310_ordinary_code_portals/function_processing.py
pythagoras/_310_ordinary_code_portals/ordinary_decorator.py
pythagoras/_310_ordinary_code_portals/ordinary_portal_core_classes.py
pythagoras/_310_ordinary_code_portals/reuse_flag.py
pythagoras/_320_logging_code_portals/__init__.py
pythagoras/_320_logging_code_portals/exception_processing_tracking.py
pythagoras/_320_logging_code_portals/execution_environment_summary.py
pythagoras/_320_logging_code_portals/logging_decorator.py
pythagoras/_320_logging_code_portals/logging_portal_core_classes.py
pythagoras/_320_logging_code_portals/uncaught_exceptions.py
pythagoras/_330_safe_code_portals/__init__.py
pythagoras-0.50.1.dist-info/METADATA
pythagoras-0.50.1.dist-info/WHEEL
pythagoras-0.50.1.dist-info/licenses/LICENSE
pythagoras-0.50.1.dist-info/RECORD
