Metadata-Version: 2.4
Name: pythagoras
Version: 0.50.1
Summary: Planet-scale distributed computing in Python.
Project-URL: Homepage, https://github.com/pythagoras-dev/pythagoras
Author-email: "Volodymyr (Vlad) Pavlov" <vlpavlov@ieee.org>
License-File: LICENSE
Keywords: AI,ML,cloud,deep-learning,distributed,machine-learning,parallel,pythagoras,serverless
Classifier: Development Status :: 3 - Alpha
Classifier: Intended Audience :: Developers
Classifier: Intended Audience :: Science/Research
Classifier: License :: OSI Approved :: MIT License
Classifier: Operating System :: OS Independent
Classifier: Programming Language :: Python
Classifier: Programming Language :: Python :: 3
Classifier: Programming Language :: Python :: 3.11
Classifier: Programming Language :: Python :: 3.12
Classifier: Programming Language :: Python :: 3.13
Classifier: Programming Language :: Python :: 3.14
Classifier: Topic :: Scientific/Engineering
Classifier: Topic :: Scientific/Engineering :: Information Analysis
Classifier: Topic :: Software Development :: Libraries
Classifier: Topic :: Software Development :: Libraries :: Python Modules
Classifier: Typing :: Typed
Requires-Python: >=3.11
Requires-Dist: autopep8
Requires-Dist: boto3
Requires-Dist: deepdiff
Requires-Dist: joblib
Requires-Dist: jsonpickle
Requires-Dist: lz4
Requires-Dist: mixinforge
Requires-Dist: numpy
Requires-Dist: pandas
Requires-Dist: persidict
Requires-Dist: psutil
Requires-Dist: scikit-learn
Requires-Dist: uv
Provides-Extra: aws
Requires-Dist: boto3; extra == 'aws'
Requires-Dist: moto; extra == 'aws'
Requires-Dist: persidict[aws]; extra == 'aws'
Provides-Extra: dev
Requires-Dist: boto3; extra == 'dev'
Requires-Dist: coverage; extra == 'dev'
Requires-Dist: keras; extra == 'dev'
Requires-Dist: moto; extra == 'dev'
Requires-Dist: numpy; extra == 'dev'
Requires-Dist: persidict[dev]; extra == 'dev'
Requires-Dist: pytest; extra == 'dev'
Requires-Dist: ruff; extra == 'dev'
Requires-Dist: scipy; extra == 'dev'
Requires-Dist: uv-publish; extra == 'dev'
Provides-Extra: nvidia
Requires-Dist: nvidia-ml-py; extra == 'nvidia'
